src/EmailMetadata.py
src/MongoDBHandler.py
src/OutlookConnector.py
src/SQLiteHandler.py
src/__init__.py
src/debug_utils.py
src/mcp_server.py
src/tools/__init__.py
src/tools/embedding_processor.py
iflow_mcp_mcp_server_outlook_email-0.1.0.dist-info/METADATA
iflow_mcp_mcp_server_outlook_email-0.1.0.dist-info/WHEEL
iflow_mcp_mcp_server_outlook_email-0.1.0.dist-info/entry_points.txt
iflow_mcp_mcp_server_outlook_email-0.1.0.dist-info/RECORD
