Metadata-Version: 2.4
Name: iflow-mcp_mcp-server-outlook-email
Version: 0.1.0
Summary: Email Processing MCP Server with MongoDB integration
Requires-Dist: fastmcp
Requires-Dist: langchain
Requires-Dist: langchain-community
Requires-Dist: langchain-core
Requires-Dist: langchain-ollama
Requires-Dist: pydantic
Requires-Dist: pymongo
Requires-Dist: python-dotenv
Requires-Dist: pytz
Requires-Dist: pywin32; sys_platform == 'win32'
